nude_classifier_2d_3d/__init__.py
nude_classifier_2d_3d/classifier.py
nude_classifier_2d_3d/models/best_efficientnet_b0.pth
nude_classifier_2d_3d-1.0.3.dist-info/LICENSE
nude_classifier_2d_3d-1.0.3.dist-info/METADATA
nude_classifier_2d_3d-1.0.3.dist-info/WHEEL
nude_classifier_2d_3d-1.0.3.dist-info/RECORD
