Metadata-Version: 2.3
Name: nude-classifier-2d-3d
Version: 1.0.3
Summary: A Python package for classifying nude images as real (3D) or drawn (2D) using a pre-trained EfficientNet-B0 model.
License: MIT
Keywords: image-classification,deep-learning,pytorch,efficientnet,nudes
Author: FINWAX
Author-email: waxbid@gmail.com
Requires-Python: >=3.10,<4.0
Classifier: License :: OSI Approved :: MIT License
Classifier: Operating System :: OS Independent
Classifier: Programming Language :: Python :: 3
Classifier: Programming Language :: Python :: 3.10
Classifier: Programming Language :: Python :: 3.11
Classifier: Programming Language :: Python :: 3.12
Classifier: Programming Language :: Python :: 3.13
Requires-Dist: pillow (>=11.0.0,<12.0.0)
Requires-Dist: torch (>=2.7.0,<3.0.0)
Requires-Dist: torchvision (>=0.22.0,<0.23.0)
Project-URL: Homepage, https://github.com/FINWAX/img-nude-as-3d-or-2d.py
Project-URL: Repository, https://github.com/FINWAX/img-nude-as-3d-or-2d.py
